README.md
setup.cfg
setup.py
o_must_gather.egg-info/PKG-INFO
o_must_gather.egg-info/SOURCES.txt
o_must_gather.egg-info/dependency_links.txt
o_must_gather.egg-info/entry_points.txt
o_must_gather.egg-info/not-zip-safe
o_must_gather.egg-info/requires.txt
o_must_gather.egg-info/top_level.txt
omg/__init__.py
omg/cli.py
omg/cmd/__init__.py
omg/cmd/describe.py
omg/cmd/get_main.py
omg/cmd/log.py
omg/cmd/project.py
omg/cmd/use.py
omg/cmd/whoami.py
omg/cmd/get/__init__.py
omg/cmd/get/bc_out.py
omg/cmd/get/build_out.py
omg/cmd/get/cj_out.py
omg/cmd/get/cm_out.py
omg/cmd/get/co_out.py
omg/cmd/get/complete_get.py
omg/cmd/get/crd_out.py
omg/cmd/get/csr_out.py
omg/cmd/get/cv_out.py
omg/cmd/get/dc_out.py
omg/cmd/get/deployment_out.py
omg/cmd/get/ds_out.py
omg/cmd/get/ep_out.py
omg/cmd/get/eps_out.py
omg/cmd/get/ev_out.py
omg/cmd/get/from_yaml.py
omg/cmd/get/get_project.py
omg/cmd/get/hpa_out.py
omg/cmd/get/is_out.py
omg/cmd/get/job_out.py
omg/cmd/get/machine_out.py
omg/cmd/get/machineset_out.py
omg/cmd/get/mc_out.py
omg/cmd/get/mcp_out.py
omg/cmd/get/mwhc_out.py
omg/cmd/get/node_out.py
omg/cmd/get/parse.py
omg/cmd/get/pod_out.py
omg/cmd/get/project_out.py
omg/cmd/get/pv_out.py
omg/cmd/get/pvc_out.py
omg/cmd/get/rc_out.py
omg/cmd/get/route_out.py
omg/cmd/get/rs_out.py
omg/cmd/get/sc_out.py
omg/cmd/get/secret_out.py
omg/cmd/get/service_out.py
omg/cmd/get/simple_out.py
omg/cmd/get/ss_out.py
omg/cmd/get/vwhc_out.py
omg/cmd/machine_config/__init__.py
omg/cmd/machine_config/compare.py
omg/cmd/machine_config/decode_content.py
omg/cmd/machine_config/extract.py
omg/cmd/machine_config/machine_config.py
omg/common/__init__.py
omg/common/config.py
omg/common/helper.py
omg/common/resource_map.py
omg/completion/__init__.py
omg/completion/bash.py
omg/test/__init__.py
omg/test/test_get_completion.py
omg/test/test_get_parse.py