Metadata-Version: 1.1
Name: o-must-gather
Version: 1.2.6
Summary: oc like tool that works with must-gather rather than OpenShift API
Home-page: https://github.com/kxr/o-must-gather
Author: Khizer Naeem
Author-email: khizernaeem@gmail.com
License: GPLv3
Platform: any
Classifier: Development Status :: 5 - Production/Stable
Classifier: Environment :: Console
Classifier: Intended Audience :: System Administrators
Classifier: License :: OSI Approved :: BSD License
Classifier: Operating System :: POSIX
Classifier: Operating System :: MacOS
Classifier: Operating System :: Unix
Classifier: Programming Language :: Python :: 3
Classifier: Topic :: Utilities
